{
  "id": "acceleron",
  "label": "Acceleron",
  "repeatable": false,
  "status": true,
  "json": {
    "Main": {
      "hero_logo": {
        "type": "Image",
        "config": {
          "label": "Logo del Hero",
          "constraint": {
            "width": 300,
            "height": 150
          },
          "thumbnails": []
        }
      },
      "hero_titulo": {
        "type": "Text",
        "config": {
          "label": "Título del Hero",
          "placeholder": "Título principal del hero"
        }
      },
      "hero_descripcion": {
        "type": "StructuredText",
        "config": {
          "label": "Descripción del Hero",
          "placeholder": "Texto descriptivo del hero",
          "multi": "paragraph,preformatted,heading1,heading2,heading3,heading4,heading5,heading6,strong,em,hyperlink,image,embed,list-item,o-list-item,rtl"
        }
      },
      "hero_imagen_fondo": {
        "type": "Image",
        "config": {
          "label": "Imagen de Fondo del Hero (Desktop)",
          "constraint": {
            "width": 1920,
            "height": 828
          },
          "thumbnails": []
        }
      },
      "hero_imagen_fondo_mobile": {
        "type": "Image",
        "config": {
          "label": "Imagen de Fondo del Hero (Mobile)",
          "constraint": {
            "width": 585,
            "height": 500
          },
          "thumbnails": []
        }
      },
      "introduccion_titulo": {
        "type": "Text",
        "config": {
          "label": "Título de Introducción",
          "placeholder": "Título de la sección de introducción"
        }
      },
      "introduccion_texto": {
        "type": "StructuredText",
        "config": {
          "label": "Texto de Introducción",
          "placeholder": "Texto descriptivo de introducción",
          "multi": "paragraph,preformatted,heading1,heading2,heading3,heading4,heading5,heading6,strong,em,hyperlink,image,embed,list-item,o-list-item,rtl"
        }
      },
      "bloques": {
        "type": "Group",
        "config": {
          "label": "Bloques de Contenido",
          "fields": {
            "imagen": {
              "type": "Image",
              "config": {
                "label": "Imagen",
                "constraint": {
                  "width": 585,
                  "height": 500
                },
                "thumbnails": []
              }
            },
            "titulo": {
              "type": "Text",
              "config": {
                "label": "Título",
                "placeholder": "Título del bloque"
              }
            },
            "descripcion": {
              "type": "StructuredText",
              "config": {
                "label": "Descripción",
                "placeholder": "Texto descriptivo del bloque",
                "multi": "paragraph,preformatted,heading1,heading2,heading3,heading4,heading5,heading6,strong,em,hyperlink,image,embed,list-item,o-list-item,rtl"
              }
            }
          }
        }
      },
      "bloque_final": {
        "type": "Group",
        "config": {
          "label": "Bloque Final",
          "fields": {
            "imagen_desktop": {
              "type": "Image",
              "config": {
                "label": "Imagen Desktop",
                "constraint": {
                  "width": 585,
                  "height": 500
                },
                "thumbnails": []
              }
            },
            "imagen_mobile": {
              "type": "Image",
              "config": {
                "label": "Imagen Mobile",
                "constraint": {
                  "width": 585,
                  "height": 500
                },
                "thumbnails": []
              }
            },
            "texto": {
              "type": "StructuredText",
              "config": {
                "label": "Texto",
                "placeholder": "Texto descriptivo",
                "multi": "paragraph,preformatted,heading1,heading2,heading3,heading4,heading5,heading6,strong,em,hyperlink,image,embed,list-item,o-list-item,rtl"
              }
            }
          }
        }
      }
    }
  }
}
